<?xml version="1.0" encoding="utf-8"?>
<odoo>
    <!-- Template base para todas las páginas EOS -->
    <template id="eos_base_template" name="EOS Base Template">
        <t t-call="web.frontend_layout">
            <t t-set="title">Mi 90 · EOS UI (ES)</t>
            <t t-set="head">
                <link rel="stylesheet" href="/mi90_eos/static/src/css/styles.css"/>
            </t>
            <t t-set="body_class">eos-dashboard</t>
        </t>
    </template>

    <!-- Dashboard principal -->
    <template id="dashboard_template" name="EOS Dashboard" inherit_id="eos_base_template">
        <t t-call="web.frontend_layout">
            <t t-set="title">Mi 90 · EOS UI (ES)</t>
            <t t-set="head">
                <link rel="stylesheet" href="/mi90_eos/static/src/css/styles.css"/>
            </t>
            <t t-set="body_class">eos-dashboard</t>
            
            <div class="topbar">
                <div class="filters">
                    <span class="pill">FILTROS</span>
                    <label>Equipo:</label>
                    <select><option>Todos</option><option>Ventas</option><option>Producción</option></select>
                </div>
                <div class="right">
                    <label>Intervalo:</label>
                    <select><option>Semanal</option><option>Mensual</option></select>
                    <label>Semanas:</label>
                    <select><option>6 (predeterminado)</option><option>8</option></select>
                    <button class="btn">Editar diseño</button>
                </div>
            </div>

            <div class="shell">
                <aside class="sidebar">
                    <div class="sb-head">Partner Hub</div>
                    <nav class="nav">
                        <a href="/eos/dashboard" class="active"><span class="icon">🏠</span><span>Mi 90</span></a>
                        <a href="/eos/scorecard"><span class="icon">📊</span><span>Scorecard</span></a>
                        <a href="/eos/rocks"><span class="icon">🪨</span><span>Rocas</span></a>
                        <a href="/eos/todos"><span class="icon">✅</span><span>To-Dos</span></a>
                        <a href="/eos/issues"><span class="icon">⚠️</span><span>Problemas</span></a>
                        <a href="/eos/meetings"><span class="icon">🗓️</span><span>Reuniones</span></a>
                        <a href="/eos/headlines"><span class="icon">📰</span><span>Titulares</span></a>
                        <a href="/eos/vto"><span class="icon">📄</span><span>V/TO®</span></a>
                        <a href="/eos/accountability"><span class="icon">👥</span><span>Organigrama de Responsabilidades</span></a>
                        <a href="/eos/oneonone"><span class="icon">👤</span><span>1-a-1</span></a>
                        <a href="/eos/process"><span class="icon">🧩</span><span>Proceso</span></a>
                        <a href="/eos/directory"><span class="icon">📇</span><span>Directorio</span></a>
                        <a href="/eos/toolbox"><span class="icon">🧰</span><span>EOS Toolbox™</span></a>
                    </nav>
                    <div class="sb-foot">
                        <nav class="nav">
                            <a href="#"><span class="icon">➕</span><span>Invitar compañeros</span></a>
                            <a href="#"><span class="icon">💬</span><span>Enviar comentarios</span></a>
                            <a href="#"><span class="icon">❓</span><span>Aprendizaje y soporte</span></a>
                        </nav>
                    </div>
                </aside>
                
                <main class="main">
                    <div class="h1">Mi 90</div>

                    <section class="card">
                        <h3>Scorecard</h3>
                        <table class="table">
                            <thead>
                                <tr>
                                    <th style="width:30%">Título</th><th>Meta</th><th>Promedio</th><th>Total</th>
                                    <th>Mar 25 – Mar 31</th><th>Mar 18 – Mar 24</th><th>Mar 11 – Mar 17</th>
                                    <th>Mar 04 – Mar 10</th><th>Feb 26 – Mar 03</th><th>Feb 19 – Feb 25</th>
                                </tr>
                            </thead>
                            <tbody>
                                <tr><td class="kpi-name"><span class="dot red"></span> Conversaciones significativas</td><td class="goal">≥ 25</td><td>16.2</td><td>97</td><td>1</td><td>17</td><td>23</td><td>22</td><td>12</td><td>22</td></tr>
                                <tr><td class="kpi-name"><span class="dot yellow"></span> Conversaciones VTH</td><td class="goal">≥ 1</td><td>1.5</td><td>9</td><td>1</td><td>1</td><td>3</td><td>2</td><td>2</td><td>1</td></tr>
                                <tr><td class="kpi-name"><span class="dot yellow"></span> 90 MM programadas</td><td class="goal">≥ 0.5</td><td>0.83</td><td>5</td><td>1</td><td>1</td><td>2</td><td>2</td><td>0</td><td>1</td></tr>
                                <tr><td class="kpi-name"><span class="dot green"></span> Nuevos clientes</td><td class="goal">≥ 0.25</td><td>0.8</td><td>4</td><td>2</td><td>0</td><td>0</td><td>2</td><td>0</td><td>0</td></tr>
                                <tr><td class="kpi-name"><span class="dot green"></span> 90 MM entregadas</td><td class="goal">≥ 0.5</td><td>1</td><td>5</td><td>1</td><td>1</td><td>1</td><td>1</td><td>0</td><td>1</td></tr>
                            </tbody>
                        </table>
                    </section>

                    <section class="grid three" style="margin-top:1rem">
                        <div class="card">
                            <h3>Tareas del equipo <span class="badge">3</span></h3>
                            <div class="todo"><span>Problema 5</span><span class="badge today">Hoy</span></div>
                            <div class="todo"><span>To‑Do #2</span><span class="badge today">Hoy</span></div>
                            <div class="todo"><span>To‑Do #4</span><span class="badge today">Hoy</span></div>
                        </div>
                        <div class="card">
                            <h3>Rocas y hitos</h3>
                            <div class="todo"><span>✅ Asegurar 3 nuevos clientes</span><span class="badge ok">31 Mar</span></div>
                            <div class="todo"><span>👍 Roca #2</span><span class="badge ok">31 Mar</span></div>
                        </div>
                        <div class="card">
                            <h3>Estados de rocas</h3>
                            <div class="pie-wrap">
                                <canvas id="rockPie" width="120" height="120"></canvas>
                                <div>
                                    <div class="kpi">3</div>
                                    <div class="pie-legend">Total</div>
                                    <div style="margin-top:.5rem">
                                        <div><span style="display:inline-block;width:10px;height:10px;background:#22c55e;border-radius:2px;margin-right:.35rem"></span>1 Completada · 33%</div>
                                        <div><span style="display:inline-block;width:10px;height:10px;background:#3b82f6;border-radius:2px;margin-right:.35rem"></span>2 En curso · 67%</div>
                                        <div><span style="display:inline-block;width:10px;height:10px;background:#ef4444;border-radius:2px;margin-right:.35rem"></span>0 Fuera de curso · 0%</div>
                                    </div>
                                </div>
                            </div>
                        </div>
                    </section>
                    
                    <div class="footer-hint">Prototipo estático para tesis · Distribución inspirada en la interfaz solicitada.</div>
                </main>
            </div>
            
            <script src="/mi90_eos/static/src/js/app.js"></script>
        </t>
    </template>

    <!-- Template para Scorecard -->
    <template id="scorecard_template" name="EOS Scorecard" inherit_id="eos_base_template">
        <t t-call="web.frontend_layout">
            <t t-set="title">Scorecard · EOS UI (ES)</t>
            <t t-set="head">
                <link rel="stylesheet" href="/mi90_eos/static/src/css/styles.css"/>
            </t>
            <t t-set="body_class">eos-dashboard</t>
            
            <div class="shell">
                <aside class="sidebar">
                    <div class="sb-head">Partner Hub</div>
                    <nav class="nav">
                        <a href="/eos/dashboard"><span class="icon">🏠</span><span>Mi 90</span></a>
                        <a href="/eos/scorecard" class="active"><span class="icon">📊</span><span>Scorecard</span></a>
                        <a href="/eos/rocks"><span class="icon">🪨</span><span>Rocas</span></a>
                        <a href="/eos/todos"><span class="icon">✅</span><span>To-Dos</span></a>
                        <a href="/eos/issues"><span class="icon">⚠️</span><span>Problemas</span></a>
                        <a href="/eos/meetings"><span class="icon">🗓️</span><span>Reuniones</span></a>
                        <a href="/eos/headlines"><span class="icon">📰</span><span>Titulares</span></a>
                        <a href="/eos/vto"><span class="icon">📄</span><span>V/TO®</span></a>
                        <a href="/eos/accountability"><span class="icon">👥</span><span>Organigrama de Responsabilidades</span></a>
                        <a href="/eos/oneonone"><span class="icon">👤</span><span>1-a-1</span></a>
                        <a href="/eos/process"><span class="icon">🧩</span><span>Proceso</span></a>
                        <a href="/eos/directory"><span class="icon">📇</span><span>Directorio</span></a>
                        <a href="/eos/toolbox"><span class="icon">🧰</span><span>EOS Toolbox™</span></a>
                    </nav>
                </aside>
                
                <main class="main">
                    <div class="h1">Scorecard</div>
                    <div class="footer-hint">Página de Scorecard EOS</div>
                </main>
            </div>
            
            <script src="/mi90_eos/static/src/js/app.js"></script>
        </t>
    </template>

    <!-- Templates para las demás páginas (simplificados) -->
    <template id="rocks_template" name="EOS Rocks" inherit_id="eos_base_template">
        <t t-call="web.frontend_layout">
            <t t-set="title">Rocas · EOS UI (ES)</t>
            <t t-set="head"><link rel="stylesheet" href="/mi90_eos/static/src/css/styles.css"/></t>
            <t t-set="body_class">eos-dashboard</t>
            <div class="shell">
                <aside class="sidebar">
                    <div class="sb-head">Partner Hub</div>
                    <nav class="nav">
                        <a href="/eos/dashboard"><span class="icon">🏠</span><span>Mi 90</span></a>
                        <a href="/eos/scorecard"><span class="icon">📊</span><span>Scorecard</span></a>
                        <a href="/eos/rocks" class="active"><span class="icon">🪨</span><span>Rocas</span></a>
                        <a href="/eos/todos"><span class="icon">✅</span><span>To-Dos</span></a>
                        <a href="/eos/issues"><span class="icon">⚠️</span><span>Problemas</span></a>
                        <a href="/eos/meetings"><span class="icon">🗓️</span><span>Reuniones</span></a>
                        <a href="/eos/headlines"><span class="icon">📰</span><span>Titulares</span></a>
                        <a href="/eos/vto"><span class="icon">📄</span><span>V/TO®</span></a>
                        <a href="/eos/accountability"><span class="icon">👥</span><span>Organigrama de Responsabilidades</span></a>
                        <a href="/eos/oneonone"><span class="icon">👤</span><span>1-a-1</span></a>
                        <a href="/eos/process"><span class="icon">🧩</span><span>Proceso</span></a>
                        <a href="/eos/directory"><span class="icon">📇</span><span>Directorio</span></a>
                        <a href="/eos/toolbox"><span class="icon">🧰</span><span>EOS Toolbox™</span></a>
                    </nav>
                </aside>
                <main class="main"><div class="h1">Rocas</div><div class="footer-hint">Página de Rocas EOS</div></main>
            </div>
            <script src="/mi90_eos/static/src/js/app.js"></script>
        </t>
    </template>

    <!-- Repetir para todas las demás páginas con estructura similar -->
    <template id="todos_template" name="EOS Todos" inherit_id="eos_base_template">
        <t t-call="web.frontend_layout">
            <t t-set="title">To-Dos · EOS UI (ES)</t>
            <t t-set="head"><link rel="stylesheet" href="/mi90_eos/static/src/css/styles.css"/></t>
            <t t-set="body_class">eos-dashboard</t>
            <div class="shell">
                <aside class="sidebar">
                    <div class="sb-head">Partner Hub</div>
                    <nav class="nav">
                        <a href="/eos/dashboard"><span class="icon">🏠</span><span>Mi 90</span></a>
                        <a href="/eos/scorecard"><span class="icon">📊</span><span>Scorecard</span></a>
                        <a href="/eos/rocks"><span class="icon">🪨</span><span>Rocas</span></a>
                        <a href="/eos/todos" class="active"><span class="icon">✅</span><span>To-Dos</span></a>
                        <a href="/eos/issues"><span class="icon">⚠️</span><span>Problemas</span></a>
                        <a href="/eos/meetings"><span class="icon">🗓️</span><span>Reuniones</span></a>
                        <a href="/eos/headlines"><span class="icon">📰</span><span>Titulares</span></a>
                        <a href="/eos/vto"><span class="icon">📄</span><span>V/TO®</span></a>
                        <a href="/eos/accountability"><span class="icon">👥</span><span>Organigrama de Responsabilidades</span></a>
                        <a href="/eos/oneonone"><span class="icon">👤</span><span>1-a-1</span></a>
                        <a href="/eos/process"><span class="icon">🧩</span><span>Proceso</span></a>
                        <a href="/eos/directory"><span class="icon">📇</span><span>Directorio</span></a>
                        <a href="/eos/toolbox"><span class="icon">🧰</span><span>EOS Toolbox™</span></a>
                    </nav>
                </aside>
                <main class="main"><div class="h1">To-Dos</div><div class="footer-hint">Página de To-Dos EOS</div></main>
            </div>
            <script src="/mi90_eos/static/src/js/app.js"></script>
        </t>
    </template>

    <!-- Continuar con el resto de templates... -->
    <template id="issues_template" name="EOS Issues" inherit_id="eos_base_template">
        <t t-call="web.frontend_layout">
            <t t-set="title">Problemas · EOS UI (ES)</t>
            <t t-set="head"><link rel="stylesheet" href="/mi90_eos/static/src/css/styles.css"/></t>
            <t t-set="body_class">eos-dashboard</t>
            <div class="shell">
                <aside class="sidebar">
                    <div class="sb-head">Partner Hub</div>
                    <nav class="nav">
                        <a href="/eos/dashboard"><span class="icon">🏠</span><span>Mi 90</span></a>
                        <a href="/eos/scorecard"><span class="icon">📊</span><span>Scorecard</span></a>
                        <a href="/eos/rocks"><span class="icon">🪨</span><span>Rocas</span></a>
                        <a href="/eos/todos"><span class="icon">✅</span><span>To-Dos</span></a>
                        <a href="/eos/issues" class="active"><span class="icon">⚠️</span><span>Problemas</span></a>
                        <a href="/eos/meetings"><span class="icon">🗓️</span><span>Reuniones</span></a>
                        <a href="/eos/headlines"><span class="icon">📰</span><span>Titulares</span></a>
                        <a href="/eos/vto"><span class="icon">📄</span><span>V/TO®</span></a>
                        <a href="/eos/accountability"><span class="icon">👥</span><span>Organigrama de Responsabilidades</span></a>
                        <a href="/eos/oneonone"><span class="icon">👤</span><span>1-a-1</span></a>
                        <a href="/eos/process"><span class="icon">🧩</span><span>Proceso</span></a>
                        <a href="/eos/directory"><span class="icon">📇</span><span>Directorio</span></a>
                        <a href="/eos/toolbox"><span class="icon">🧰</span><span>EOS Toolbox™</span></a>
                    </nav>
                </aside>
                <main class="main"><div class="h1">Problemas</div><div class="footer-hint">Página de Problemas EOS</div></main>
            </div>
            <script src="/mi90_eos/static/src/js/app.js"></script>
        </t>
    </template>

    <!-- Templates restantes con estructura similar -->
    <template id="meetings_template" name="EOS Meetings" inherit_id="eos_base_template">
        <t t-call="web.frontend_layout">
            <t t-set="title">Reuniones · EOS UI (ES)</t>
            <t t-set="head"><link rel="stylesheet" href="/mi90_eos/static/src/css/styles.css"/></t>
            <t t-set="body_class">eos-dashboard</t>
            <div class="shell">
                <aside class="sidebar">
                    <div class="sb-head">Partner Hub</div>
                    <nav class="nav">
                        <a href="/eos/dashboard"><span class="icon">🏠</span><span>Mi 90</span></a>
                        <a href="/eos/scorecard"><span class="icon">📊</span><span>Scorecard</span></a>
                        <a href="/eos/rocks"><span class="icon">🪨</span><span>Rocas</span></a>
                        <a href="/eos/todos"><span class="icon">✅</span><span>To-Dos</span></a>
                        <a href="/eos/issues"><span class="icon">⚠️</span><span>Problemas</span></a>
                        <a href="/eos/meetings" class="active"><span class="icon">🗓️</span><span>Reuniones</span></a>
                        <a href="/eos/headlines"><span class="icon">📰</span><span>Titulares</span></a>
                        <a href="/eos/vto"><span class="icon">📄</span><span>V/TO®</span></a>
                        <a href="/eos/accountability"><span class="icon">👥</span><span>Organigrama de Responsabilidades</span></a>
                        <a href="/eos/oneonone"><span class="icon">👤</span><span>1-a-1</span></a>
                        <a href="/eos/process"><span class="icon">🧩</span><span>Proceso</span></a>
                        <a href="/eos/directory"><span class="icon">📇</span><span>Directorio</span></a>
                        <a href="/eos/toolbox"><span class="icon">🧰</span><span>EOS Toolbox™</span></a>
                    </nav>
                </aside>
                <main class="main"><div class="h1">Reuniones</div><div class="footer-hint">Página de Reuniones EOS</div></main>
            </div>
            <script src="/mi90_eos/static/src/js/app.js"></script>
        </t>
    </template>

    <template id="headlines_template" name="EOS Headlines" inherit_id="eos_base_template">
        <t t-call="web.frontend_layout">
            <t t-set="title">Titulares · EOS UI (ES)</t>
            <t t-set="head"><link rel="stylesheet" href="/mi90_eos/static/src/css/styles.css"/></t>
            <t t-set="body_class">eos-dashboard</t>
            <div class="shell">
                <aside class="sidebar">
                    <div class="sb-head">Partner Hub</div>
                    <nav class="nav">
                        <a href="/eos/dashboard"><span class="icon">🏠</span><span>Mi 90</span></a>
                        <a href="/eos/scorecard"><span class="icon">📊</span><span>Scorecard</span></a>
                        <a href="/eos/rocks"><span class="icon">🪨</span><span>Rocas</span></a>
                        <a href="/eos/todos"><span class="icon">✅</span><span>To-Dos</span></a>
                        <a href="/eos/issues"><span class="icon">⚠️</span><span>Problemas</span></a>
                        <a href="/eos/meetings"><span class="icon">🗓️</span><span>Reuniones</span></a>
                        <a href="/eos/headlines" class="active"><span class="icon">📰</span><span>Titulares</span></a>
                        <a href="/eos/vto"><span class="icon">📄</span><span>V/TO®</span></a>
                        <a href="/eos/accountability"><span class="icon">👥</span><span>Organigrama de Responsabilidades</span></a>
                        <a href="/eos/oneonone"><span class="icon">👤</span><span>1-a-1</span></a>
                        <a href="/eos/process"><span class="icon">🧩</span><span>Proceso</span></a>
                        <a href="/eos/directory"><span class="icon">📇</span><span>Directorio</span></a>
                        <a href="/eos/toolbox"><span class="icon">🧰</span><span>EOS Toolbox™</span></a>
                    </nav>
                </aside>
                <main class="main"><div class="h1">Titulares</div><div class="footer-hint">Página de Titulares EOS</div></main>
            </div>
            <script src="/mi90_eos/static/src/js/app.js"></script>
        </t>
    </template>

    <template id="vto_template" name="EOS VTO" inherit_id="eos_base_template">
        <t t-call="web.frontend_layout">
            <t t-set="title">V/TO® · EOS UI (ES)</t>
            <t t-set="head"><link rel="stylesheet" href="/mi90_eos/static/src/css/styles.css"/></t>
            <t t-set="body_class">eos-dashboard</t>
            <div class="shell">
                <aside class="sidebar">
                    <div class="sb-head">Partner Hub</div>
                    <nav class="nav">
                        <a href="/eos/dashboard"><span class="icon">🏠</span><span>Mi 90</span></a>
                        <a href="/eos/scorecard"><span class="icon">📊</span><span>Scorecard</span></a>
                        <a href="/eos/rocks"><span class="icon">🪨</span><span>Rocas</span></a>
                        <a href="/eos/todos"><span class="icon">✅</span><span>To-Dos</span></a>
                        <a href="/eos/issues"><span class="icon">⚠️</span><span>Problemas</span></a>
                        <a href="/eos/meetings"><span class="icon">🗓️</span><span>Reuniones</span></a>
                        <a href="/eos/headlines"><span class="icon">📰</span><span>Titulares</span></a>
                        <a href="/eos/vto" class="active"><span class="icon">📄</span><span>V/TO®</span></a>
                        <a href="/eos/accountability"><span class="icon">👥</span><span>Organigrama de Responsabilidades</span></a>
                        <a href="/eos/oneonone"><span class="icon">👤</span><span>1-a-1</span></a>
                        <a href="/eos/process"><span class="icon">🧩</span><span>Proceso</span></a>
                        <a href="/eos/directory"><span class="icon">📇</span><span>Directorio</span></a>
                        <a href="/eos/toolbox"><span class="icon">🧰</span><span>EOS Toolbox™</span></a>
                    </nav>
                </aside>
                <main class="main"><div class="h1">V/TO®</div><div class="footer-hint">Página de V/TO® EOS</div></main>
            </div>
            <script src="/mi90_eos/static/src/js/app.js"></script>
        </t>
    </template>

    <template id="accountability_template" name="EOS Accountability" inherit_id="eos_base_template">
        <t t-call="web.frontend_layout">
            <t t-set="title">Organigrama de Responsabilidades · EOS UI (ES)</t>
            <t t-set="head"><link rel="stylesheet" href="/mi90_eos/static/src/css/styles.css"/></t>
            <t t-set="body_class">eos-dashboard</t>
            <div class="shell">
                <aside class="sidebar">
                    <div class="sb-head">Partner Hub</div>
                    <nav class="nav">
                        <a href="/eos/dashboard"><span class="icon">🏠</span><span>Mi 90</span></a>
                        <a href="/eos/scorecard"><span class="icon">📊</span><span>Scorecard</span></a>
                        <a href="/eos/rocks"><span class="icon">🪨</span><span>Rocas</span></a>
                        <a href="/eos/todos"><span class="icon">✅</span><span>To-Dos</span></a>
                        <a href="/eos/issues"><span class="icon">⚠️</span><span>Problemas</span></a>
                        <a href="/eos/meetings"><span class="icon">🗓️</span><span>Reuniones</span></a>
                        <a href="/eos/headlines"><span class="icon">📰</span><span>Titulares</span></a>
                        <a href="/eos/vto"><span class="icon">📄</span><span>V/TO®</span></a>
                        <a href="/eos/accountability" class="active"><span class="icon">👥</span><span>Organigrama de Responsabilidades</span></a>
                        <a href="/eos/oneonone"><span class="icon">👤</span><span>1-a-1</span></a>
                        <a href="/eos/process"><span class="icon">🧩</span><span>Proceso</span></a>
                        <a href="/eos/directory"><span class="icon">📇</span><span>Directorio</span></a>
                        <a href="/eos/toolbox"><span class="icon">🧰</span><span>EOS Toolbox™</span></a>
                    </nav>
                </aside>
                <main class="main"><div class="h1">Organigrama de Responsabilidades</div><div class="footer-hint">Página de Organigrama de Responsabilidades EOS</div></main>
            </div>
            <script src="/mi90_eos/static/src/js/app.js"></script>
        </t>
    </template>

    <template id="oneonone_template" name="EOS One on One" inherit_id="eos_base_template">
        <t t-call="web.frontend_layout">
            <t t-set="title">1-a-1 · EOS UI (ES)</t>
            <t t-set="head"><link rel="stylesheet" href="/mi90_eos/static/src/css/styles.css"/></t>
            <t t-set="body_class">eos-dashboard</t>
            <div class="shell">
                <aside class="sidebar">
                    <div class="sb-head">Partner Hub</div>
                    <nav class="nav">
                        <a href="/eos/dashboard"><span class="icon">🏠</span><span>Mi 90</span></a>
                        <a href="/eos/scorecard"><span class="icon">📊</span><span>Scorecard</span></a>
                        <a href="/eos/rocks"><span class="icon">🪨</span><span>Rocas</span></a>
                        <a href="/eos/todos"><span class="icon">✅</span><span>To-Dos</span></a>
                        <a href="/eos/issues"><span class="icon">⚠️</span><span>Problemas</span></a>
                        <a href="/eos/meetings"><span class="icon">🗓️</span><span>Reuniones</span></a>
                        <a href="/eos/headlines"><span class="icon">📰</span><span>Titulares</span></a>
                        <a href="/eos/vto"><span class="icon">📄</span><span>V/TO®</span></a>
                        <a href="/eos/accountability"><span class="icon">👥</span><span>Organigrama de Responsabilidades</span></a>
                        <a href="/eos/oneonone" class="active"><span class="icon">👤</span><span>1-a-1</span></a>
                        <a href="/eos/process"><span class="icon">🧩</span><span>Proceso</span></a>
                        <a href="/eos/directory"><span class="icon">📇</span><span>Directorio</span></a>
                        <a href="/eos/toolbox"><span class="icon">🧰</span><span>EOS Toolbox™</span></a>
                    </nav>
                </aside>
                <main class="main"><div class="h1">1-a-1</div><div class="footer-hint">Página de 1-a-1 EOS</div></main>
            </div>
            <script src="/mi90_eos/static/src/js/app.js"></script>
        </t>
    </template>

    <template id="process_template" name="EOS Process" inherit_id="eos_base_template">
        <t t-call="web.frontend_layout">
            <t t-set="title">Proceso · EOS UI (ES)</t>
            <t t-set="head"><link rel="stylesheet" href="/mi90_eos/static/src/css/styles.css"/></t>
            <t t-set="body_class">eos-dashboard</t>
            <div class="shell">
                <aside class="sidebar">
                    <div class="sb-head">Partner Hub</div>
                    <nav class="nav">
                        <a href="/eos/dashboard"><span class="icon">🏠</span><span>Mi 90</span></a>
                        <a href="/eos/scorecard"><span class="icon">📊</span><span>Scorecard</span></a>
                        <a href="/eos/rocks"><span class="icon">🪨</span><span>Rocas</span></a>
                        <a href="/eos/todos"><span class="icon">✅</span><span>To-Dos</span></a>
                        <a href="/eos/issues"><span class="icon">⚠️</span><span>Problemas</span></a>
                        <a href="/eos/meetings"><span class="icon">🗓️</span><span>Reuniones</span></a>
                        <a href="/eos/headlines"><span class="icon">📰</span><span>Titulares</span></a>
                        <a href="/eos/vto"><span class="icon">📄</span><span>V/TO®</span></a>
                        <a href="/eos/accountability"><span class="icon">👥</span><span>Organigrama de Responsabilidades</span></a>
                        <a href="/eos/oneonone"><span class="icon">👤</span><span>1-a-1</span></a>
                        <a href="/eos/process" class="active"><span class="icon">🧩</span><span>Proceso</span></a>
                        <a href="/eos/directory"><span class="icon">📇</span><span>Directorio</span></a>
                        <a href="/eos/toolbox"><span class="icon">🧰</span><span>EOS Toolbox™</span></a>
                    </nav>
                </aside>
                <main class="main"><div class="h1">Proceso</div><div class="footer-hint">Página de Proceso EOS</div></main>
            </div>
            <script src="/mi90_eos/static/src/js/app.js"></script>
        </t>
    </template>

    <template id="directory_template" name="EOS Directory" inherit_id="eos_base_template">
        <t t-call="web.frontend_layout">
            <t t-set="title">Directorio · EOS UI (ES)</t>
            <t t-set="head"><link rel="stylesheet" href="/mi90_eos/static/src/css/styles.css"/></t>
            <t t-set="body_class">eos-dashboard</t>
            <div class="shell">
                <aside class="sidebar">
                    <div class="sb-head">Partner Hub</div>
                    <nav class="nav">
                        <a href="/eos/dashboard"><span class="icon">🏠</span><span>Mi 90</span></a>
                        <a href="/eos/scorecard"><span class="icon">📊</span><span>Scorecard</span></a>
                        <a href="/eos/rocks"><span class="icon">🪨</span><span>Rocas</span></a>
                        <a href="/eos/todos"><span class="icon">✅</span><span>To-Dos</span></a>
                        <a href="/eos/issues"><span class="icon">⚠️</span><span>Problemas</span></a>
                        <a href="/eos/meetings"><span class="icon">🗓️</span><span>Reuniones</span></a>
                        <a href="/eos/headlines"><span class="icon">📰</span><span>Titulares</span></a>
                        <a href="/eos/vto"><span class="icon">📄</span><span>V/TO®</span></a>
                        <a href="/eos/accountability"><span class="icon">👥</span><span>Organigrama de Responsabilidades</span></a>
                        <a href="/eos/oneonone"><span class="icon">👤</span><span>1-a-1</span></a>
                        <a href="/eos/process"><span class="icon">🧩</span><span>Proceso</span></a>
                        <a href="/eos/directory" class="active"><span class="icon">📇</span><span>Directorio</span></a>
                        <a href="/eos/toolbox"><span class="icon">🧰</span><span>EOS Toolbox™</span></a>
                    </nav>
                </aside>
                <main class="main"><div class="h1">Directorio</div><div class="footer-hint">Página de Directorio EOS</div></main>
            </div>
            <script src="/mi90_eos/static/src/js/app.js"></script>
        </t>
    </template>

    <template id="toolbox_template" name="EOS Toolbox" inherit_id="eos_base_template">
        <t t-call="web.frontend_layout">
            <t t-set="title">EOS Toolbox™ · EOS UI (ES)</t>
            <t t-set="head"><link rel="stylesheet" href="/mi90_eos/static/src/css/styles.css"/></t>
            <t t-set="body_class">eos-dashboard</t>
            <div class="shell">
                <aside class="sidebar">
                    <div class="sb-head">Partner Hub</div>
                    <nav class="nav">
                        <a href="/eos/dashboard"><span class="icon">🏠</span><span>Mi 90</span></a>
                        <a href="/eos/scorecard"><span class="icon">📊</span><span>Scorecard</span></a>
                        <a href="/eos/rocks"><span class="icon">🪨</span><span>Rocas</span></a>
                        <a href="/eos/todos"><span class="icon">✅</span><span>To-Dos</span></a>
                        <a href="/eos/issues"><span class="icon">⚠️</span><span>Problemas</span></a>
                        <a href="/eos/meetings"><span class="icon">🗓️</span><span>Reuniones</span></a>
                        <a href="/eos/headlines"><span class="icon">📰</span><span>Titulares</span></a>
                        <a href="/eos/vto"><span class="icon">📄</span><span>V/TO®</span></a>
                        <a href="/eos/accountability"><span class="icon">👥</span><span>Organigrama de Responsabilidades</span></a>
                        <a href="/eos/oneonone"><span class="icon">👤</span><span>1-a-1</span></a>
                        <a href="/eos/process"><span class="icon">🧩</span><span>Proceso</span></a>
                        <a href="/eos/directory"><span class="icon">📇</span><span>Directorio</span></a>
                        <a href="/eos/toolbox" class="active"><span class="icon">🧰</span><span>EOS Toolbox™</span></a>
                    </nav>
                </aside>
                <main class="main"><div class="h1">EOS Toolbox™</div><div class="footer-hint">Página de EOS Toolbox™</div></main>
            </div>
            <script src="/mi90_eos/static/src/js/app.js"></script>
        </t>
    </template>

</odoo>
